result_32 bit ram/design.sv
///Day-50
///DATE:-19/02/2024
///32-BIT RAM

module Day_50(input clk, wr, rd, rst,
              input [31:0] data_in,
              input [5:0] addr,
              output [31:0] data_out);
  reg [31:0] ram [0:31];

    always @(posedge clk) begin
        if(rst) begin
          ram[addr] <= 32'd0;
        end
        else begin
            if(wr)
                ram[addr] <= data_in;
        end
    end

  assign data_out = rd ? ram[addr] : 64'dz;
endmodule

result_32 bit ram/testbench.sv
module Day_50_tb();
  reg clk, wr, rd, rst;
  reg [31:0] data_in;
  wire [31:0] data_out;
  reg [8:0] addr;
  integer i;

  Day_50 uut(clk, wr, rd, rst, data_in, addr, data_out);

  always #5 clk = ~clk;

  initial clk = 0;

  initial begin
    $dumpfile("dump.vcd");       // Create VCD file
    $dumpvars(0, Day_50_tb);
    wr = 1'b1;
    rd = 1'b0;
    rst = 1'b1;
    #10;
    rst = 1'b0;

    for (i = 0; i < 15; i = i + 1) begin
      wr = 1'b1;
      data_in = $random();
      addr = i;
      $display("wr=%b, data_in=%d, addr=%d", wr, data_in, addr);
      #10;
    end

    wr = 1'b0;
    rd = 1'b1;

    for (i = 0; i < 15; i = i + 1) begin
      addr = i;
      $display("rd=%b, addr=%d, data_out=%d", wr, addr, data_out);
      #10;
    end

    #400;
    $finish();
  end
endmodule

result_32 bit ram/dump.vcd
$date
	Wed May 13 08:32:09 2026
$end

$version
	Synopsys VCS version X-2025.06-SP1_Full64
$end

$timescale
	1ns
$end

$comment Csum: 1 aad18e7b22b7dbb6 $end


$scope module Day_50_tb $end
$var reg 1 ! clk $end
$var reg 1 " wr $end
$var reg 1 # rd $end
$var reg 1 $ rst $end
$var reg 32 % data_in [31:0] $end
$var wire 32 & data_out [31:0] $end
$var reg 9 ' addr [8:0] $end
$var integer 32 ( i $end

$scope module uut $end
$var wire 1 ! clk $end
$var wire 1 " wr $end
$var wire 1 # rd $end
$var wire 1 $ rst $end
$var wire 32 % data_in [31:0] $end
$var wire 6 ) addr [5:0] $end
$var wire 32 & data_out [31:0] $end
$upscope $end

$upscope $end

$enddefinitions $end

#0
$dumpvars
0!
0#
1$
1"
bxxxxxxxxx '
bxxxxxxxxxxxxxxxxxxxxxxxxxxxxxxxx %
bzzzzzzzzzzzzzzzzzzzzzzzzzzzzzzzz &
bxxxxxxxxxxxxxxxxxxxxxxxxxxxxxxxx (
bxxxxxx )
$end
#5
1!
#10
0$
b00000000000000000000000000000000 (
b00010010000101010011010100100100 %
b000000000 '
b000000 )
0!
#15
1!
#20
b00000000000000000000000000000001 (
b11000000100010010101111010000001 %
b000000001 '
b000001 )
0!
#25
1!
#30
b00000000000000000000000000000010 (
b10000100100001001101011000001001 %
b000000010 '
b000010 )
0!
#35
1!
#40
b00000000000000000000000000000011 (
b10110001111100000101011001100011 %
b000000011 '
b000011 )
0!
#45
1!
#50
b00000000000000000000000000000100 (
b00000110101110010111101100001101 %
b000000100 '
b000100 )
0!
#55
1!
#60
b00000000000000000000000000000101 (
b01000110110111111001100110001101 %
b000000101 '
b000101 )
0!
#65
1!
#70
b00000000000000000000000000000110 (
b10110010110000101000010001100101 %
b000000110 '
b000110 )
0!
#75
1!
#80
b00000000000000000000000000000111 (
b10001001001101110101001000010010 %
b000000111 '
b000111 )
0!
#85
1!
#90
b00000000000000000000000000001000 (
b00000000111100111110001100000001 %
b000001000 '
b001000 )
0!
#95
1!
#100
b00000000000000000000000000001001 (
b00000110110101111100110100001101 %
b000001001 '
b001001 )
0!
#105
1!
#110
b00000000000000000000000000001010 (
b00111011001000111111000101110110 %
b000001010 '
b001010 )
0!
#115
1!
#120
b00000000000000000000000000001011 (
b00011110100011011100110100111101 %
b000001011 '
b001011 )
0!
#125
1!
#130
b00000000000000000000000000001100 (
b01110110110101000101011111101101 %
b000001100 '
b001100 )
0!
#135
1!
#140
b00000000000000000000000000001101 (
b01000110001011011111011110001100 %
b000001101 '
b001101 )
0!
#145
1!
#150
b00000000000000000000000000001110 (
b01111100111111011110100111111001 %
b000001110 '
b001110 )
0!
#155
1!
#160
b00000000000000000000000000001111 (
0"
1#
b00000000000000000000000000000000 (
b000000000 '
b000000 )
0!
b00010010000101010011010100100100 &
#165
1!
#170
b00000000000000000000000000000001 (
b000000001 '
b000001 )
0!
b11000000100010010101111010000001 &
#175
1!
#180
b00000000000000000000000000000010 (
b000000010 '
b000010 )
0!
b10000100100001001101011000001001 &
#185
1!
#190
b00000000000000000000000000000011 (
b000000011 '
b000011 )
0!
b10110001111100000101011001100011 &
#195
1!
#200
b00000000000000000000000000000100 (
b000000100 '
b000100 )
0!
b00000110101110010111101100001101 &
#205
1!
#210
b00000000000000000000000000000101 (
b000000101 '
b000101 )
0!
b01000110110111111001100110001101 &
#215
1!
#220
b00000000000000000000000000000110 (
b000000110 '
b000110 )
0!
b10110010110000101000010001100101 &
#225
1!
#230
b00000000000000000000000000000111 (
b000000111 '
b000111 )
0!
b10001001001101110101001000010010 &
#235
1!
#240
b00000000000000000000000000001000 (
b000001000 '
b001000 )
0!
b00000000111100111110001100000001 &
#245
1!
#250
b00000000000000000000000000001001 (
b000001001 '
b001001 )
0!
b00000110110101111100110100001101 &
#255
1!
#260
b00000000000000000000000000001010 (
b000001010 '
b001010 )
0!
b00111011001000111111000101110110 &
#265
1!
#270
b00000000000000000000000000001011 (
b000001011 '
b001011 )
0!
b00011110100011011100110100111101 &
#275
1!
#280
b00000000000000000000000000001100 (
b000001100 '
b001100 )
0!
b01110110110101000101011111101101 &
#285
1!
#290
b00000000000000000000000000001101 (
b000001101 '
b001101 )
0!
b01000110001011011111011110001100 &
#295
1!
#300
b00000000000000000000000000001110 (
b000001110 '
b001110 )
0!
b01111100111111011110100111111001 &
#305
1!
#310
b00000000000000000000000000001111 (
0!
